pdf2markdown/__about__.py
pdf2markdown/__init__.py
pdf2markdown/__main__.py
pdf2markdown/api/__init__.py
pdf2markdown/api/config.py
pdf2markdown/api/converter.py
pdf2markdown/api/exceptions.py
pdf2markdown/api/types.py
pdf2markdown/cli/main.py
pdf2markdown/config/__init__.py
pdf2markdown/config/schemas.py
pdf2markdown/config/settings.py
pdf2markdown/core/__init__.py
pdf2markdown/core/exceptions.py
pdf2markdown/core/interfaces.py
pdf2markdown/core/models.py
pdf2markdown/llm_providers/__init__.py
pdf2markdown/llm_providers/base.py
pdf2markdown/llm_providers/factory.py
pdf2markdown/llm_providers/openai.py
pdf2markdown/llm_providers/transformers.py
pdf2markdown/parsers/__init__.py
pdf2markdown/parsers/document/__init__.py
pdf2markdown/parsers/document/base.py
pdf2markdown/parsers/document/simple.py
pdf2markdown/parsers/page/__init__.py
pdf2markdown/parsers/page/base.py
pdf2markdown/parsers/page/simple_llm.py
pdf2markdown/pipeline/__init__.py
pdf2markdown/pipeline/coordinator.py
pdf2markdown/pipeline/global_manager.py
pdf2markdown/pipeline/progress.py
pdf2markdown/pipeline/queue_manager.py
pdf2markdown/pipeline/worker.py
pdf2markdown/templates/prompts/ocr_extraction.j2
pdf2markdown/utils/__init__.py
pdf2markdown/utils/cache_manager.py
pdf2markdown/utils/logger.py
pdf2markdown/utils/markdown_cleaner.py
pdf2markdown/utils/statistics.py
pdf2markdown/validators/__init__.py
pdf2markdown/validators/base.py
pdf2markdown/validators/factory.py
pdf2markdown/validators/markdown_validator.py
pdf2markdown/validators/repetition_validator.py
pdf2markdown-0.3.0.dist-info/METADATA
pdf2markdown-0.3.0.dist-info/WHEEL
pdf2markdown-0.3.0.dist-info/entry_points.txt
pdf2markdown-0.3.0.dist-info/licenses/LICENSE
pdf2markdown-0.3.0.dist-info/RECORD
