Metadata-Version: 2.4
Name: pdf2markdown
Version: 0.3.0
Summary: Python library and CLI tool that leverages LLMs to convert technical PDF documents to well-structured Markdown
Project-URL: Documentation, https://github.com/juanqui/pdf2markdown#readme
Project-URL: Issues, https://github.com/juanqui/pdf2markdown/issues
Project-URL: Source, https://github.com/juanqui/pdf2markdown
Author-email: Juan Villa <juanqui@villafam.com>
Maintainer-email: Juan Villa <juanqui@villafam.com>
License-Expression: MIT
License-File: LICENSE
Keywords: ai,conversion,document-conversion,document-processing,gpt,llm,machine-learning,markdown,ocr,openai,pdf,pdf-parser,pdf-to-text,transformers,vision
Classifier: Development Status :: 4 - Beta
Classifier: Environment :: Console
Classifier: Framework :: AsyncIO
Classifier: Intended Audience :: Developers
Classifier: Intended Audience :: Information Technology
Classifier: Intended Audience :: Science/Research
Classifier: License :: OSI Approved :: MIT License
Classifier: Operating System :: OS Independent
Classifier: Programming Language :: Python
Classifier: Programming Language :: Python :: 3
Classifier: Programming Language :: Python :: 3.10
Classifier: Programming Language :: Python :: 3.11
Classifier: Programming Language :: Python :: 3.12
Classifier: Programming Language :: Python :: Implementation :: CPython
Classifier: Topic :: Multimedia :: Graphics :: Graphics Conversion
Classifier: Topic :: Scientific/Engineering :: Artificial Intelligence
Classifier: Topic :: Software Development :: Libraries :: Python Modules
Classifier: Topic :: Text Processing :: Markup :: Markdown
Requires-Python: >=3.10
Requires-Dist: aiofiles>=23.0.0
Requires-Dist: aiohttp>=3.9.0
Requires-Dist: click>=8.1.0
Requires-Dist: httpx>=0.25.0
Requires-Dist: jinja2>=3.1.0
Requires-Dist: openai>=1.0.0
Requires-Dist: pillow>=10.0.0
Requires-Dist: pydantic>=2.0.0
Requires-Dist: pymarkdownlnt>=0.9.12
Requires-Dist: pymupdf>=1.23.0
Requires-Dist: python-dotenv>=1.0.0
Requires-Dist: pyyaml>=6.0
Requires-Dist: rich>=13.0.0
Requires-Dist: tenacity>=8.2.0
Provides-Extra: transformers
Requires-Dist: accelerate>=0.25.0; extra == 'transformers'
Requires-Dist: einops>=0.7.0; extra == 'transformers'
Requires-Dist: protobuf>=3.20.0; extra == 'transformers'
Requires-Dist: sentencepiece>=0.1.99; extra == 'transformers'
Requires-Dist: torch>=2.0.0; extra == 'transformers'
Requires-Dist: torchvision>=0.15.0; extra == 'transformers'
Requires-Dist: transformers>=4.36.0; extra == 'transformers'
